gunshotmatch_method_writer/_pycode/README.md
gunshotmatch_method_writer/_pycode/__init__.py
gunshotmatch_method_writer/_pycode/parser.py
gunshotmatch_method_writer/__init__.py
gunshotmatch_method_writer/py.typed
gunshotmatch_method_writer-0.2.0.dist-info/LICENSE
gunshotmatch_method_writer-0.2.0.dist-info/METADATA
gunshotmatch_method_writer-0.2.0.dist-info/WHEEL
gunshotmatch_method_writer-0.2.0.dist-info/entry_points.txt
gunshotmatch_method_writer-0.2.0.dist-info/RECORD
