Metadata-Version: 2.2
Name: gunshotmatch-method-writer
Version: 0.2.0
Summary: Method writer for GunShotMatch.
Author-email: Dominic Davis-Foster <dominic@davis-foster.co.uk>
License: BSD-3-Clause
Home-page: https://github.com/GunShotMatch/gunshotmatch-method-writer
Project-URL: Issue Tracker, https://github.com/GunShotMatch/gunshotmatch-method-writer/issues
Project-URL: Source Code, https://github.com/GunShotMatch/gunshotmatch-method-writer
Platform: Windows
Platform: macOS
Platform: Linux
Classifier: Development Status :: 3 - Alpha
Classifier: Intended Audience :: Developers
Classifier: License :: OSI Approved :: BSD License
Classifier: Operating System :: OS Independent
Classifier: Programming Language :: Python
Classifier: Programming Language :: Python :: 3 :: Only
Classifier: Programming Language :: Python :: 3.8
Classifier: Programming Language :: Python :: 3.9
Classifier: Programming Language :: Python :: 3.10
Classifier: Programming Language :: Python :: 3.11
Classifier: Programming Language :: Python :: 3.12
Classifier: Programming Language :: Python :: Implementation :: CPython
Classifier: Topic :: Software Development :: Libraries :: Python Modules
Classifier: Typing :: Typed
Requires-Python: >=3.8
Requires-Dist: attrs>=23.2.0
Requires-Dist: dom-toml[config]>=2.2.0
Requires-Dist: domdf-python-tools>=3.8.0.post2
Requires-Dist: tomli-w>=1.0.0
